text_theme_scribe/__init__.py
text_theme_scribe/main.py
text_theme_scribe/prompts.py
text_theme_scribe-2025.12.21184024.dist-info/METADATA
text_theme_scribe-2025.12.21184024.dist-info/WHEEL
text_theme_scribe-2025.12.21184024.dist-info/top_level.txt
text_theme_scribe-2025.12.21184024.dist-info/RECORD
