Metadata-Version: 2.4
Name: text-theme-scribe
Version: 2025.12.21184024
Summary: text-theme-scribe extracts recurring themes from text and returns a structured list of key concepts via LLM, ensuring consistent formatting.
Author-email: text-theme-scribe <hi@eugene.plus>
License: MIT
Project-URL: Homepage, https://github.com/chigwell/text-theme-scribe
Requires-Python: >=3.9
Requires-Dist: langchain-llm7>=0.0.0
Requires-Dist: llmatch-messages>=0.0.0
Requires-Dist: langchain-core>=0.3.0
